pve2.py
setup.py
pve2.egg-info/PKG-INFO
pve2.egg-info/SOURCES.txt
pve2.egg-info/dependency_links.txt
pve2.egg-info/requires.txt
pve2.egg-info/top_level.txt